<?xml version='1.0' encoding='UTF-8'?>
<notas_fiscais>
<DataEmissao>20/01/2020</DataEmissao>
<NotaFiscal>10493</NotaFiscal>
<Warehouse>WHPOA</Warehouse>
<CidadeOrigem>Porto Alegre</CidadeOrigem>
<CidadeDestino>Belo Horizonte</CidadeDestino>
<CodCliente>4039</CodCliente>
<TotalNotaFiscal>3657,43</TotalNotaFiscal>
<Volumes>11</Volumes>
<PesoBruto>12,815</PesoBruto>
<CodTransportadora>6100231</CodTransportadora>
<Transportadora>Cargo Centro-Oeste</Transportadora>
<CentroDistribuicao>Goiania</CentroDistribuicao>
<TipoTransporte>Convencional</TipoTransporte>
<PrazoContratado>3</PrazoContratado>
<DataColeta>21/01/2020</DataColeta>
<DataEntrega>23/01/2020</DataEntrega>
<Ocorrencia>Nenhuma</Ocorrencia>
</notas_fiscais>
