<?xml version='1.0' encoding='UTF-8'?>
<notas_fiscais>
<DataEmissao>12/05/2020</DataEmissao>
<NotaFiscal>10883</NotaFiscal>
<Warehouse>WHSJC</Warehouse>
<CidadeOrigem>Sao Jose dos Campos</CidadeOrigem>
<CidadeDestino>Belo Horizonte</CidadeDestino>
<CodCliente>4095</CodCliente>
<TotalNotaFiscal>978,93</TotalNotaFiscal>
<Volumes>1</Volumes>
<PesoBruto>1,12</PesoBruto>
<CodTransportadora>6140092</CodTransportadora>
<Transportadora>RodoCarioca</Transportadora>
<CentroDistribuicao>Rio de Janeiro</CentroDistribuicao>
<TipoTransporte>Convencional</TipoTransporte>
<PrazoContratado>4</PrazoContratado>
<DataColeta>12/05/2020</DataColeta>
<DataEntrega>13/05/2020</DataEntrega>
<Ocorrencia>Nenhuma</Ocorrencia>
</notas_fiscais>
