<?xml version='1.0' encoding='UTF-8'?>
<notas_fiscais>
<DataEmissao>16/06/2020</DataEmissao>
<NotaFiscal>10984</NotaFiscal>
<Warehouse>WHSJC</Warehouse>
<CidadeOrigem>Sao Jose dos Campos</CidadeOrigem>
<CidadeDestino>Manaus</CidadeDestino>
<CodCliente>4045</CodCliente>
<TotalNotaFiscal>2279,38</TotalNotaFiscal>
<Volumes>7</Volumes>
<PesoBruto>7,154</PesoBruto>
<CodTransportadora>6600879</CodTransportadora>
<Transportadora>Transportadora Mineira</Transportadora>
<CentroDistribuicao>Belo Horizonte</CentroDistribuicao>
<TipoTransporte>Convencional</TipoTransporte>
<PrazoContratado>8</PrazoContratado>
<DataColeta>16/06/2020</DataColeta>
<DataEntrega>19/06/2020</DataEntrega>
<Ocorrencia>Nenhuma</Ocorrencia>
</notas_fiscais>
