<?xml version='1.0' encoding='UTF-8'?>
<notas_fiscais>
<DataEmissao>29/12/2020</DataEmissao>
<NotaFiscal>11614</NotaFiscal>
<Warehouse>WHSAO</Warehouse>
<CidadeOrigem>Sao Paulo</CidadeOrigem>
<CidadeDestino>Belo Horizonte</CidadeDestino>
<CodCliente>4037</CodCliente>
<TotalNotaFiscal>246,35</TotalNotaFiscal>
<Volumes>1</Volumes>
<PesoBruto>0,171</PesoBruto>
<CodTransportadora>6100231</CodTransportadora>
<Transportadora>Cargo Centro-Oeste</Transportadora>
<CentroDistribuicao>Goiania</CentroDistribuicao>
<TipoTransporte>Convencional</TipoTransporte>
<PrazoContratado>2</PrazoContratado>
<DataColeta>29/12/2020</DataColeta>
<DataEntrega>08/01/2021</DataEntrega>
<Ocorrencia>Nenhuma</Ocorrencia>
</notas_fiscais>
