<?xml version='1.0' encoding='UTF-8'?>
<notas_fiscais>
<DataEmissao>22/06/2021</DataEmissao>
<NotaFiscal>12266</NotaFiscal>
<Warehouse>WHRJ</Warehouse>
<CidadeOrigem>Rio De Janeiro</CidadeOrigem>
<CidadeDestino>Porto Alegre</CidadeDestino>
<CodCliente>4027</CodCliente>
<TotalNotaFiscal>741,9</TotalNotaFiscal>
<Volumes>1</Volumes>
<PesoBruto>6,024</PesoBruto>
<CodTransportadora>6500948</CodTransportadora>
<Transportadora>Gaucho Transportes</Transportadora>
<CentroDistribuicao>Porto Alegre</CentroDistribuicao>
<TipoTransporte>Convencional</TipoTransporte>
<PrazoContratado>3</PrazoContratado>
<DataColeta>22/06/2021</DataColeta>
<DataEntrega>29/06/2021</DataEntrega>
<Ocorrencia>Nenhuma</Ocorrencia>
</notas_fiscais>
