<?xml version='1.0' encoding='UTF-8'?>
<notas_fiscais>
<DataEmissao>09/10/2021</DataEmissao>
<NotaFiscal>12844</NotaFiscal>
<Warehouse>WHCPQ</Warehouse>
<CidadeOrigem>Campinas</CidadeOrigem>
<CidadeDestino>Sao Paulo</CidadeDestino>
<CodCliente>4060</CodCliente>
<TotalNotaFiscal>321,17</TotalNotaFiscal>
<Volumes>4</Volumes>
<PesoBruto>7,816</PesoBruto>
<CodTransportadora>6100231</CodTransportadora>
<Transportadora>Cargo Centro-Oeste</Transportadora>
<CentroDistribuicao>Goiania</CentroDistribuicao>
<TipoTransporte>Convencional</TipoTransporte>
<PrazoContratado>3</PrazoContratado>
<DataColeta>09/10/2021</DataColeta>
<DataEntrega>19/10/2021</DataEntrega>
<Ocorrencia>Nenhuma</Ocorrencia>
</notas_fiscais>
