<?xml version='1.0' encoding='UTF-8'?>
<notas_fiscais>
<DataEmissao>03/12/2021</DataEmissao>
<NotaFiscal>13068</NotaFiscal>
<Warehouse>WHBH</Warehouse>
<CidadeOrigem>Belo Horizonte</CidadeOrigem>
<CidadeDestino>Porto Alegre</CidadeDestino>
<CodCliente>4205</CodCliente>
<TotalNotaFiscal>280,43</TotalNotaFiscal>
<Volumes>1</Volumes>
<PesoBruto>0,105</PesoBruto>
<CodTransportadora>6600879</CodTransportadora>
<Transportadora>Transportadora Mineira</Transportadora>
<CentroDistribuicao>Belo Horizonte</CentroDistribuicao>
<TipoTransporte>Convencional</TipoTransporte>
<PrazoContratado>10</PrazoContratado>
<DataColeta>04/12/2021</DataColeta>
<DataEntrega>08/12/2021</DataEntrega>
<Ocorrencia>Nenhuma</Ocorrencia>
</notas_fiscais>
